indpy/__init__.py
indpy/cli.py
indpy/generators.py
indpy/utils.py
indpy/validators.py
indpy_core-0.1.4.dist-info/LICENSE
indpy_core-0.1.4.dist-info/METADATA
indpy_core-0.1.4.dist-info/WHEEL
indpy_core-0.1.4.dist-info/entry_points.txt
indpy_core-0.1.4.dist-info/top_level.txt
indpy_core-0.1.4.dist-info/RECORD
