Metadata-Version: 2.1
Name: indpy-core
Version: 0.1.4
Summary: A comprehensive library for Indian Identity and Financial data validation.
Home-page: https://github.com/harshgupta2125/Indpy
Author: Harsh Gupta
Author-email: Harsh Gupta <harsh2125gupta@gmail.com>
License: MIT
Project-URL: Homepage, https://github.com/harshgupta2125/Indpy
Project-URL: Bug Tracker, https://github.com/harshgupta2125/Indpy/issues
Classifier: Programming Language :: Python :: 3
Classifier: License :: OSI Approved :: MIT License
Classifier: Operating System :: OS Independent
Classifier: Development Status :: 3 - Alpha
Classifier: Intended Audience :: Developers
Classifier: Topic :: Software Development :: Libraries :: Python Modules
Requires-Python: >=3.6
License-File: LICENSE
